dora_vad/__init__.py
dora_vad/main.py
dora_vad-0.4.1.dist-info/METADATA
dora_vad-0.4.1.dist-info/WHEEL
dora_vad-0.4.1.dist-info/entry_points.txt
dora_vad-0.4.1.dist-info/top_level.txt
dora_vad-0.4.1.dist-info/RECORD
