Metadata-Version: 2.4
Name: dora-vad
Version: 0.4.1
Summary: Dora Node for Text translating using Argostranslate
Author-email: Haixuan Xavier Tao <tao.xavier@outlook.com>
License: MIT
Requires-Python: >=3.8
Requires-Dist: dora-rs>=0.3.9
Requires-Dist: numpy<2.0.0
Requires-Dist: silero-vad>=5.1
